pyvera/__init__.py
pyvera-0.3.15.dist-info/LICENSE
pyvera-0.3.15.dist-info/WHEEL
pyvera-0.3.15.dist-info/METADATA
pyvera-0.3.15.dist-info/RECORD
