Metadata-Version: 2.1
Name: pyvera
Version: 0.3.15
Summary: Python API for talking to Veracontrollers
Home-page: https://github.com/pavoni/pyvera
License: GPL2
Keywords: vera,api
Author: James Cole
Requires-Python: >=3.5,<4.0
Classifier: License :: Other/Proprietary License
Classifier: Programming Language :: Python :: 3
Classifier: Programming Language :: Python :: 3.10
Classifier: Programming Language :: Python :: 3.5
Classifier: Programming Language :: Python :: 3.6
Classifier: Programming Language :: Python :: 3.7
Classifier: Programming Language :: Python :: 3.8
Classifier: Programming Language :: Python :: 3.9
Requires-Dist: requests (>=2.22.0)
Project-URL: Repository, https://github.com/pavoni/pyvera
